nosql_yorm/__init__.py
nosql_yorm/cache.py
nosql_yorm/config.py
nosql_yorm/default_config.yaml
nosql_yorm/examples/saving_cache.py
nosql_yorm/initializers/firebase_initializer.py
nosql_yorm/models.py
nosql_yorm/utils.py
nosql_yorm-0.2.1.dist-info/LICENSE
nosql_yorm-0.2.1.dist-info/METADATA
nosql_yorm-0.2.1.dist-info/WHEEL
nosql_yorm-0.2.1.dist-info/RECORD
